{
    "$schema": "https://json-schema.org/draft/2020-12/schema",
    "$id": "https://schemas.cerberauth.com/openid/draft/2024-09/provider.schema.json",
    "title": "OpenID Connect Provider",
    "description": "",
    "type": "object",
    "required": [
        "name",
        "identifier",
        "license"
    ],
    "properties": {
        "name": {
            "type": "string"
        },
        "abstract": {
            "type": "string"
        },
        "identifier": {
            "type": "string"
        },
        "website": {
            "type": "string",
            "format": "uri"
        },
        "github": {
            "type": "string",
            "format": "uri"
        },
        "icon": {
            "$ref": "https://schemas.cerberauth.com/content/draft/2024-09/image.schema.json"
        },
        "license": {
            "type": "string"
        },
        "softwareVersion": {
            "type": "string"
        },
        "featureList": {
            "type": "array",
            "items": {
                "$ref": "https://schemas.cerberauth.com/content/draft/2024-09/feature.schema.json"
            }
        }
    }
}